brane/__init__.py
brane/__main__.py
brane/typing.py
brane/config/__init__.py
brane/config/formats/basic.yaml
brane/config/formats/core.yaml
brane/config/hooks/core.yaml
brane/config/modules/basic.yaml
brane/config/modules/core.yaml
brane/config/objects/basic.yaml
brane/config/objects/core.yaml
brane/core/__init__.py
brane/core/base.py
brane/core/event.py
brane/core/factory.py
brane/core/format.py
brane/core/hook.py
brane/core/iomanager.py
brane/core/mapper.py
brane/core/module.py
brane/core/object.py
brane/core/utils.py
brane/core/xio.py
brane/libs/__init__.py
brane/libs/hooks/__init__.py
brane/libs/hooks/core.py
brane/libs/hooks/image.py
brane-0.0.dev1.dist-info/LICENSE
brane-0.0.dev1.dist-info/METADATA
brane-0.0.dev1.dist-info/WHEEL
brane-0.0.dev1.dist-info/top_level.txt
brane-0.0.dev1.dist-info/RECORD
