Metadata-Version: 2.1
Name: brane
Version: 0.0.dev1
Home-page: https://nrakwtnb.github.io/brane/
Author: Noriaki Watanabe
Author-email: noriaki.mathphys+brane-py@gmail.com
License: Apache License 2.0
Keywords: I/O management,I/O hook
Classifier: Development Status :: 1 - Planning
Classifier: License :: OSI Approved :: Apache Software License
Classifier: Operating System :: OS Independent
Classifier: Programming Language :: Python
Classifier: Programming Language :: Python :: 3
Classifier: Programming Language :: Python :: 3 :: Only
Classifier: Programming Language :: Python :: 3.7
Classifier: Programming Language :: Python :: 3.8
Classifier: Programming Language :: Python :: 3.9
Classifier: Programming Language :: Python :: 3.10
Classifier: Programming Language :: Python :: 3.11
Classifier: Programming Language :: Python :: 3.12
Classifier: Topic :: Scientific/Engineering
Classifier: Topic :: Software Development
Requires-Python: >=3.7.2
License-File: LICENSE
Requires-Dist: PyYAML (>=5.1)
Requires-Dist: fsspec (>=2021.4.0)
Requires-Dist: typing-extensions ; python_version < "3.9"
Provides-Extra: gcs
Requires-Dist: gcsfs ; extra == 'gcs'
Provides-Extra: s3
Requires-Dist: s3fs ; extra == 's3'
